querido_diario/__init__.py
querido_diario_api_wrapper-0.0.2.dist-info/LICENSE
querido_diario_api_wrapper-0.0.2.dist-info/METADATA
querido_diario_api_wrapper-0.0.2.dist-info/WHEEL
querido_diario_api_wrapper-0.0.2.dist-info/top_level.txt
querido_diario_api_wrapper-0.0.2.dist-info/RECORD
