Metadata-Version: 2.1
Name: querido-diario-api-wrapper
Version: 0.0.2
Summary: CLI for Querido Diário API
Home-page: http://github.com/rennerocha/querido-diario-api-wrapper
Author: Renne Rocha
Author-email: renne@rocha.dev.br
License: MIT
Platform: UNKNOWN
Requires-Dist: requests
